id/__init__.py
id/id_service/__init__.py
id/id_service/id_server.py
id/id_service/magenid/__init__.py
id/id_service/magenid/idsapp/__init__.py
id/id_service/magenid/idsapp/settings.py
id/id_service/magenid/idsapp/idsserver/__init__.py
id/id_service/magenid/idsapp/idsserver/lib/__init__.py
id/id_service/magenid/idsapp/idsserver/lib/autenticator.py
id/id_service/magenid/idsapp/idsserver/lib/bll/__init__.py
id/id_service/magenid/idsapp/idsserver/lib/bll/client_api.py
id/id_service/magenid/idsapp/idsserver/lib/bll/group_api.py
id/id_service/magenid/idsapp/idsserver/lib/bll/user_api.py
id/id_service/magenid/idsapp/idsserver/lib/db/__init__.py
id/id_service/magenid/idsapp/idsserver/lib/db/dao.py
id/id_service/magenid/idsapp/idsserver/lib/db/db_exception_handler.py
id/id_service/magenid/idsapp/idsserver/lib/db/magen_client_dao.py
id/id_service/magenid/idsapp/idsserver/lib/db/magen_group_dao.py
id/id_service/magenid/idsapp/idsserver/lib/db/magen_user_dao.py
id/id_service/magenid/idsapp/idsserver/lib/db/models/__init__.py
id/id_service/magenid/idsapp/idsserver/lib/db/models/magen_client_models.py
id/id_service/magenid/idsapp/idsserver/lib/db/models/models.py
id/id_service/magenid/idsapp/idsserver/lib/oidc/__init__.py
id/id_service/magenid/idsapp/idsserver/lib/oidc/exception_handler.py
id/id_service/magenid/idsapp/idsserver/lib/oidc/oauth_exception_handler.py
id/id_service/magenid/idsapp/idsserver/lib/oidc/oidc_provider.py
id/id_service/magenid/idsapp/idsserver/rest/__init__.py
id/id_service/magenid/idsapp/idsserver/rest/authorize_rest_api.py
id/id_service/magenid/idsapp/idsserver/rest/magen_client_rest_api.py
id/id_service/magenid/idsapp/idsserver/rest/magen_group_rest_api.py
id/id_service/magenid/idsapp/idsserver/rest/magen_user_rest_api.py
id/id_service/magenid/idsapp/idsserver/utils/__init__.py
id/id_service/magenid/idsapp/idsserver/utils/dd_events.py
id/id_service/magenid/idsapp/idsserver/utils/utilities.py
magen_id_service-1.0a2.dist-info/DESCRIPTION.rst
magen_id_service-1.0a2.dist-info/METADATA
magen_id_service-1.0a2.dist-info/RECORD
magen_id_service-1.0a2.dist-info/WHEEL
magen_id_service-1.0a2.dist-info/metadata.json
magen_id_service-1.0a2.dist-info/top_level.txt
